minio_helper/__init__.py
minio_helper/minio_helper.py
minio_helper-0.0.1.dist-info/LICENSE
minio_helper-0.0.1.dist-info/METADATA
minio_helper-0.0.1.dist-info/WHEEL
minio_helper-0.0.1.dist-info/top_level.txt
minio_helper-0.0.1.dist-info/RECORD
