Metadata-Version: 2.1
Name: minio_helper
Version: 0.0.1
Summary: Minio helper utility for digital-club project
Author: Frank Maduka
License: MIT
License-File: LICENSE
